pytmod/__init__.py
pytmod/_version.py
pytmod/eig.py
pytmod/helpers.py
pytmod/material.py
pytmod/slab.py
pytmod-0.0.1.dist-info/METADATA
pytmod-0.0.1.dist-info/WHEEL
pytmod-0.0.1.dist-info/licenses/LICENSE.txt
pytmod-0.0.1.dist-info/RECORD
