Metadata-Version: 2.4
Name: pytmod
Version: 0.0.1
Summary: Time modulated wave solver
Project-URL: Homepage, https://bvial.info/pytmod
Project-URL: Documentation, https://bvial.info/pytmod
Project-URL: Repository, https://github.com/benvial/pytmod
Project-URL: Issues, https://github.com/benvial/pytmod/issues
Author: Benjamin Vial
Author-email: benjamin.vial84@gmail.com
License:                     GNU GENERAL PUBLIC LICENSE
License-File: LICENSE.txt
Keywords: electromagnetism,optics,time-modulated
Classifier: Development Status :: 1 - Planning
Classifier: Intended Audience :: Science/Research
Classifier: License :: OSI Approved :: MIT License
Classifier: Operating System :: OS Independent
Classifier: Programming Language :: Python
Classifier: Programming Language :: Python :: 3
Classifier: Programming Language :: Python :: 3.10
Classifier: Programming Language :: Python :: 3.11
Classifier: Programming Language :: Python :: 3.12
Classifier: Programming Language :: Python :: 3.13
Classifier: Topic :: Scientific/Engineering
Classifier: Topic :: Scientific/Engineering :: Mathematics
Classifier: Topic :: Scientific/Engineering :: Physics
Classifier: Topic :: Utilities
Requires-Python: >=3.10
Requires-Dist: matplotlib>=3.7.0
Requires-Dist: numpy>=1.20.0
Requires-Dist: scikit-image>=0.19.3
Requires-Dist: scipy>=1.10.0
Provides-Extra: dev
Requires-Dist: hatch; extra == 'dev'
Requires-Dist: hatch-vcs; extra == 'dev'
Requires-Dist: ipython; extra == 'dev'
Requires-Dist: nox; extra == 'dev'
Requires-Dist: pre-commit; extra == 'dev'
Requires-Dist: uv; extra == 'dev'
Provides-Extra: doc
Requires-Dist: linkify-it-py; extra == 'doc'
Requires-Dist: memory-profiler; extra == 'doc'
Requires-Dist: myst-parser; extra == 'doc'
Requires-Dist: numpydoc; extra == 'doc'
Requires-Dist: pandas; extra == 'doc'
Requires-Dist: shibuya; extra == 'doc'
Requires-Dist: sphinx; extra == 'doc'
Requires-Dist: sphinx-autoapi; extra == 'doc'
Requires-Dist: sphinx-design; extra == 'doc'
Requires-Dist: sphinx-gallery; extra == 'doc'
Requires-Dist: sphinx-multiversion; extra == 'doc'
Requires-Dist: sphinx-tabs; extra == 'doc'
Requires-Dist: sphinx-togglebutton; extra == 'doc'
Requires-Dist: sphinxcontrib-bibtex; extra == 'doc'
Requires-Dist: sphinxcontrib-video; extra == 'doc'
Provides-Extra: test
Requires-Dist: coverage; extra == 'test'
Requires-Dist: pytest; extra == 'test'
Requires-Dist: pytest-cov; extra == 'test'
Requires-Dist: pytest-datadir; extra == 'test'
Requires-Dist: pytest-sugar; extra == 'test'
Requires-Dist: pytest-xdist[psutil]; extra == 'test'
